thumbnail_maker/__init__.py
thumbnail_maker/__main__.py
thumbnail_maker/cli.py
thumbnail_maker/renderer.py
thumbnail_maker/upload.py
thumbnail_maker/gui/__init__.py
thumbnail_maker/gui/dsl_manager.py
thumbnail_maker/gui/font_utils.py
thumbnail_maker/gui/handlers.py
thumbnail_maker/gui/main_window.py
thumbnail_maker/gui/preview_thread.py
thumbnail_maker/gui/widgets.py
thumbnail_maker-0.1.11.dist-info/METADATA
thumbnail_maker-0.1.11.dist-info/WHEEL
thumbnail_maker-0.1.11.dist-info/entry_points.txt
thumbnail_maker-0.1.11.dist-info/RECORD
