Metadata-Version: 2.4
Name: thumbnail-maker
Version: 0.1.11
Summary: 썸네일 생성 도구 - Pillow와 PySide6 기반
Requires-Python: >=3.10
Requires-Dist: fonttools>=4.47.0
Requires-Dist: httpx>=0.28.1
Requires-Dist: loguru>=0.7.3
Requires-Dist: pillow>=10.0.0
Requires-Dist: pyside6>=6.10.0
Requires-Dist: requests>=2.31.0
Requires-Dist: uv-easy>=0.2.5
